smartargs/__init__.py
smartargs/smartargs.py
smartargs-1.0.3.dist-info/LICENSE
smartargs-1.0.3.dist-info/METADATA
smartargs-1.0.3.dist-info/WHEEL
smartargs-1.0.3.dist-info/top_level.txt
smartargs-1.0.3.dist-info/RECORD
